[{"p":{"type":"uri","value":"http://www.w3.org/1999/02/22-rdf-syntax-ns#type"},"o":{"type":"uri","value":"http://www.w3.org/2002/07/owl#Thing"}},{"p":{"type":"uri","value":"http://www.w3.org/1999/02/22-rdf-syntax-ns#type"},"o":{"type":"uri","value":"http://dbpedia.org/ontology/%3Chttp://purl.org/dc/terms/Jurisdiction%3E"}},{"p":{"type":"uri","value":"http://www.w3.org/1999/02/22-rdf-syntax-ns#type"},"o":{"type":"uri","value":"http://dbpedia.org/ontology/AdministrativeRegion"}},{"p":{"type":"uri","value":"http://www.w3.org/1999/02/22-rdf-syntax-ns#type"},"o":{"type":"uri","value":"http://dbpedia.org/ontology/Location"}},{"p":{"type":"uri","value":"http://www.w3.org/1999/02/22-rdf-syntax-ns#type"},"o":{"type":"uri","value":"http://dbpedia.org/ontology/Place"}},{"p":{"type":"uri","value":"http://www.w3.org/1999/02/22-rdf-syntax-ns#type"},"o":{"type":"uri","value":"http://dbpedia.org/ontology/PopulatedPlace"}},{"p":{"type":"uri","value":"http://www.w3.org/1999/02/22-rdf-syntax-ns#type"},"o":{"type":"uri","value":"http://dbpedia.org/ontology/Region"}},{"p":{"type":"uri","value":"http://www.w3.org/1999/02/22-rdf-syntax-ns#type"},"o":{"type":"uri","value":"http://schema.org/AdministrativeArea"}},{"p":{"type":"uri","value":"http://www.w3.org/1999/02/22-rdf-syntax-ns#type"},"o":{"type":"uri","value":"http://schema.org/Place"}},{"p":{"type":"uri","value":"http://www.w3.org/1999/02/22-rdf-syntax-ns#type"},"o":{"type":"uri","value":"http://www.wikidata.org/entity/Q3455524"}},{"p":{"type":"uri","value":"http://www.w3.org/1999/02/22-rdf-syntax-ns#type"},"o":{"type":"uri","value":"http://www.wikidata.org/entity/Q486972"}},{"p":{"type":"uri","value":"http://www.w3.org/2000/01/rdf-schema#label"},"o":{"type":"literal","xml:lang":"ja","value":"東京都"}},{"p":{"type":"uri","value":"http://www.w3.org/2000/01/rdf-schema#comment"},"o":{"type":"literal","xml:lang":"ja","value":"東京都（とうきょうと）は、日本国の首都であり、関東地方に位置する広域地方公共団体（都道府県）の一つである。東京特別区、多摩地域、島嶼部（大島・三宅・八丈・小笠原）を管轄する。都庁所在地は新宿区。英語での都公認の表記は Tokyo Metropolis で、そのほかには Tokyo Prefecture と Tokyo Metropolitan Prefecture がある。"}},{"p":{"type":"uri","value":"http://www.w3.org/2002/07/owl#sameAs"},"o":{"type":"uri","value":"http://dbpedia.org/resource/Tokyo"}},{"p":{"type":"uri","value":"http://www.w3.org/2002/07/owl#sameAs"},"o":{"type":"uri","value":"http://www.wikidata.org/entity/Q1490"}},{"p":{"type":"uri","value":"http://www.w3.org/2002/07/owl#sameAs"},"o":{"type":"uri","value":"http://af.dbpedia.org/resource/Tokio"}},{"p":{"type":"uri","value":"http://www.w3.org/2002/07/owl#sameAs"},"o":{"type":"uri","value":"http://als.dbpedia.org/resource/Tokio"}},{"p":{"type":"uri","value":"http://www.w3.org/2002/07/owl#sameAs"},"o":{"type":"uri","value":"http://am.dbpedia.org/resource/ቶክዮ"}},{"p":{"type":"uri","value":"http://www.w3.org/2002/07/owl#sameAs"},"o":{"type":"uri","value":"http://an.dbpedia.org/resource/Tokio"}},{"p":{"type":"uri","value":"http://www.w3.org/2002/07/owl#sameAs"},"o":{"type":"uri","value":"http://ar.dbpedia.org/resource/طوكيو"}},{"p":{"type":"uri","value":"http://www.w3.org/2002/07/owl#sameAs"},"o":{"type":"uri","value":"http://arz.dbpedia.org/resource/طوكيو"}},{"p":{"type":"uri","value":"http://www.w3.org/2002/07/owl#sameAs"},"o":{"type":"uri","value":"http://ast.dbpedia.org/resource/Tokyo"}},{"p":{"type":"uri","value":"http://www.w3.org/2002/07/owl#sameAs"},"o":{"type":"uri","value":"http://az.dbpedia.org/resource/Tokio"}},{"p":{"type":"uri","value":"http://www.w3.org/2002/07/owl#sameAs"},"o":{"type":"uri","value":"http://ba.dbpedia.org/resource/Токио"}},{"p":{"type":"uri","value":"http://www.w3.org/2002/07/owl#sameAs"},"o":{"type":"uri","value":"http://bar.dbpedia.org/resource/Präfektur_Tokio"}},{"p":{"type":"uri","value":"http://www.w3.org/2002/07/owl#sameAs"},"o":{"type":"uri","value":"http://be.dbpedia.org/resource/Горад_Токіа"}},{"p":{"type":"uri","value":"http://www.w3.org/2002/07/owl#sameAs"},"o":{"type":"uri","value":"http://bg.dbpedia.org/resource/Токио"}},{"p":{"type":"uri","value":"http://www.w3.org/2002/07/owl#sameAs"},"o":{"type":"uri","value":"http://bn.dbpedia.org/resource/টোকিও"}},{"p":{"type":"uri","value":"http://www.w3.org/2002/07/owl#sameAs"},"o":{"type":"uri","value":"http://br.dbpedia.org/resource/Tokyo"}},{"p":{"type":"uri","value":"http://www.w3.org/2002/07/owl#sameAs"},"o":{"type":"uri","value":"http://bs.dbpedia.org/resource/Tokio"}},{"p":{"type":"uri","value":"http://www.w3.org/2002/07/owl#sameAs"},"o":{"type":"uri","value":"http://ca.dbpedia.org/resource/Tòquio"}},{"p":{"type":"uri","value":"http://www.w3.org/2002/07/owl#sameAs"},"o":{"type":"uri","value":"http://ce.dbpedia.org/resource/Токио"}},{"p":{"type":"uri","value":"http://www.w3.org/2002/07/owl#sameAs"},"o":{"type":"uri","value":"http://ceb.dbpedia.org/resource/Tokyo"}},{"p":{"type":"uri","value":"http://www.w3.org/2002/07/owl#sameAs"},"o":{"type":"uri","value":"http://ckb.dbpedia.org/resource/تۆکیۆ"}},{"p":{"type":"uri","value":"http://www.w3.org/2002/07/owl#sameAs"},"o":{"type":"uri","value":"http://commons.dbpedia.org/resource/東京"}},{"p":{"type":"uri","value":"http://www.w3.org/2002/07/owl#sameAs"},"o":{"type":"uri","value":"http://cs.dbpedia.org/resource/Prefektura_Tokio"}},{"p":{"type":"uri","value":"http://www.w3.org/2002/07/owl#sameAs"},"o":{"type":"uri","value":"http://cv.dbpedia.org/resource/Токио"}},{"p":{"type":"uri","value":"http://www.w3.org/2002/07/owl#sameAs"},"o":{"type":"uri","value":"http://cy.dbpedia.org/resource/Tokyo"}},{"p":{"type":"uri","value":"http://www.w3.org/2002/07/owl#sameAs"},"o":{"type":"uri","value":"http://da.dbpedia.org/resource/Tokyo"}},{"p":{"type":"uri","value":"http://www.w3.org/2002/07/owl#sameAs"},"o":{"type":"uri","value":"http://de.dbpedia.org/resource/Präfektur_Tokio"}},{"p":{"type":"uri","value":"http://www.w3.org/2002/07/owl#sameAs"},"o":{"type":"uri","value":"http://el.dbpedia.org/resource/Τόκιο"}},{"p":{"type":"uri","value":"http://www.w3.org/2002/07/owl#sameAs"},"o":{"type":"uri","value":"http://eo.dbpedia.org/resource/Tokio"}},{"p":{"type":"uri","value":"http://www.w3.org/2002/07/owl#sameAs"},"o":{"type":"uri","value":"http://es.dbpedia.org/resource/Tokio"}},{"p":{"type":"uri","value":"http://www.w3.org/2002/07/owl#sameAs"},"o":{"type":"uri","value":"http://et.dbpedia.org/resource/Tōkyō_prefektuur"}},{"p":{"type":"uri","value":"http://www.w3.org/2002/07/owl#sameAs"},"o":{"type":"uri","value":"http://eu.dbpedia.org/resource/Tokio"}},{"p":{"type":"uri","value":"http://www.w3.org/2002/07/owl#sameAs"},"o":{"type":"uri","value":"http://fa.dbpedia.org/resource/توکیو"}},{"p":{"type":"uri","value":"http://www.w3.org/2002/07/owl#sameAs"},"o":{"type":"uri","value":"http://fi.dbpedia.org/resource/Tokio"}},{"p":{"type":"uri","value":"http://www.w3.org/2002/07/owl#sameAs"},"o":{"type":"uri","value":"http://fo.dbpedia.org/resource/Tokyo"}},{"p":{"type":"uri","value":"http://www.w3.org/2002/07/owl#sameAs"},"o":{"type":"uri","value":"http://fr.dbpedia.org/resource/Tokyo"}},{"p":{"type":"uri","value":"http://www.w3.org/2002/07/owl#sameAs"},"o":{"type":"uri","value":"http://fy.dbpedia.org/resource/Tokio"}},{"p":{"type":"uri","value":"http://www.w3.org/2002/07/owl#sameAs"},"o":{"type":"uri","value":"http://ga.dbpedia.org/resource/Tóiceo"}},{"p":{"type":"uri","value":"http://www.w3.org/2002/07/owl#sameAs"},"o":{"type":"uri","value":"http://gd.dbpedia.org/resource/Tokyo"}},{"p":{"type":"uri","value":"http://www.w3.org/2002/07/owl#sameAs"},"o":{"type":"uri","value":"http://gl.dbpedia.org/resource/Toquio"}},{"p":{"type":"uri","value":"http://www.w3.org/2002/07/owl#sameAs"},"o":{"type":"uri","value":"http://he.dbpedia.org/resource/טוקיו"}},{"p":{"type":"uri","value":"http://www.w3.org/2002/07/owl#sameAs"},"o":{"type":"uri","value":"http://hi.dbpedia.org/resource/टोक्यो"}},{"p":{"type":"uri","value":"http://www.w3.org/2002/07/owl#sameAs"},"o":{"type":"uri","value":"http://hr.dbpedia.org/resource/Tokio"}},{"p":{"type":"uri","value":"http://www.w3.org/2002/07/owl#sameAs"},"o":{"type":"uri","value":"http://ht.dbpedia.org/resource/Tokyo"}},{"p":{"type":"uri","value":"http://www.w3.org/2002/07/owl#sameAs"},"o":{"type":"uri","value":"http://hu.dbpedia.org/resource/Tokió"}},{"p":{"type":"uri","value":"http://www.w3.org/2002/07/owl#sameAs"},"o":{"type":"uri","value":"http://hy.dbpedia.org/resource/Տոկիո"}},{"p":{"type":"uri","value":"http://www.w3.org/2002/07/owl#sameAs"},"o":{"type":"uri","value":"http://ia.dbpedia.org/resource/Tokyo"}},{"p":{"type":"uri","value":"http://www.w3.org/2002/07/owl#sameAs"},"o":{"type":"uri","value":"http://id.dbpedia.org/resource/Tokyo"}},{"p":{"type":"uri","value":"http://www.w3.org/2002/07/owl#sameAs"},"o":{"type":"uri","value":"http://io.dbpedia.org/resource/Tokyo"}},{"p":{"type":"uri","value":"http://www.w3.org/2002/07/owl#sameAs"},"o":{"type":"uri","value":"http://is.dbpedia.org/resource/Tókýó"}},{"p":{"type":"uri","value":"http://www.w3.org/2002/07/owl#sameAs"},"o":{"type":"uri","value":"http://it.dbpedia.org/resource/Tokyo"}},{"p":{"type":"uri","value":"http://www.w3.org/2002/07/owl#sameAs"},"o":{"type":"uri","value":"http://jv.dbpedia.org/resource/Tokyo"}},{"p":{"type":"uri","value":"http://www.w3.org/2002/07/owl#sameAs"},"o":{"type":"uri","value":"http://ka.dbpedia.org/resource/ტოკიო"}},{"p":{"type":"uri","value":"http://www.w3.org/2002/07/owl#sameAs"},"o":{"type":"uri","value":"http://kk.dbpedia.org/resource/Токио"}},{"p":{"type":"uri","value":"http://www.w3.org/2002/07/owl#sameAs"},"o":{"type":"uri","value":"http://kn.dbpedia.org/resource/ಟೋಕ್ಯೊ"}},{"p":{"type":"uri","value":"http://www.w3.org/2002/07/owl#sameAs"},"o":{"type":"uri","value":"http://ko.dbpedia.org/resource/도쿄_도"}},{"p":{"type":"uri","value":"http://www.w3.org/2002/07/owl#sameAs"},"o":{"type":"uri","value":"http://ku.dbpedia.org/resource/Tokyo"}},{"p":{"type":"uri","value":"http://www.w3.org/2002/07/owl#sameAs"},"o":{"type":"uri","value":"http://ky.dbpedia.org/resource/Токио"}},{"p":{"type":"uri","value":"http://www.w3.org/2002/07/owl#sameAs"},"o":{"type":"uri","value":"http://la.dbpedia.org/resource/Tokium"}},{"p":{"type":"uri","value":"http://www.w3.org/2002/07/owl#sameAs"},"o":{"type":"uri","value":"http://lb.dbpedia.org/resource/Prefektur_Tokio"}},{"p":{"type":"uri","value":"http://www.w3.org/2002/07/owl#sameAs"},"o":{"type":"uri","value":"http://lmo.dbpedia.org/resource/Tokyo"}},{"p":{"type":"uri","value":"http://www.w3.org/2002/07/owl#sameAs"},"o":{"type":"uri","value":"http://lt.dbpedia.org/resource/Tokijas"}},{"p":{"type":"uri","value":"http://www.w3.org/2002/07/owl#sameAs"},"o":{"type":"uri","value":"http://lv.dbpedia.org/resource/Tokija"}},{"p":{"type":"uri","value":"http://www.w3.org/2002/07/owl#sameAs"},"o":{"type":"uri","value":"http://mg.dbpedia.org/resource/Tokyo"}},{"p":{"type":"uri","value":"http://www.w3.org/2002/07/owl#sameAs"},"o":{"type":"uri","value":"http://mk.dbpedia.org/resource/Токио"}},{"p":{"type":"uri","value":"http://www.w3.org/2002/07/owl#sameAs"},"o":{"type":"uri","value":"http://ml.dbpedia.org/resource/ടോക്കിയോ"}},{"p":{"type":"uri","value":"http://www.w3.org/2002/07/owl#sameAs"},"o":{"type":"uri","value":"http://mn.dbpedia.org/resource/Токио"}},{"p":{"type":"uri","value":"http://www.w3.org/2002/07/owl#sameAs"},"o":{"type":"uri","value":"http://mr.dbpedia.org/resource/तोक्यो"}},{"p":{"type":"uri","value":"http://www.w3.org/2002/07/owl#sameAs"},"o":{"type":"uri","value":"http://ms.dbpedia.org/resource/Tokyo"}},{"p":{"type":"uri","value":"http://www.w3.org/2002/07/owl#sameAs"},"o":{"type":"uri","value":"http://my.dbpedia.org/resource/တိုကျိုမြို့"}},{"p":{"type":"uri","value":"http://www.w3.org/2002/07/owl#sameAs"},"o":{"type":"uri","value":"http://mzn.dbpedia.org/resource/توکيو"}},{"p":{"type":"uri","value":"http://www.w3.org/2002/07/owl#sameAs"},"o":{"type":"uri","value":"http://nah.dbpedia.org/resource/Toquio"}},{"p":{"type":"uri","value":"http://www.w3.org/2002/07/owl#sameAs"},"o":{"type":"uri","value":"http://nap.dbpedia.org/resource/Tokyo"}},{"p":{"type":"uri","value":"http://www.w3.org/2002/07/owl#sameAs"},"o":{"type":"uri","value":"http://nds.dbpedia.org/resource/Tokio"}},{"p":{"type":"uri","value":"http://www.w3.org/2002/07/owl#sameAs"},"o":{"type":"uri","value":"http://ne.dbpedia.org/resource/टोकियो"}},{"p":{"type":"uri","value":"http://www.w3.org/2002/07/owl#sameAs"},"o":{"type":"uri","value":"http://new.dbpedia.org/resource/तोक्यो"}},{"p":{"type":"uri","value":"http://www.w3.org/2002/07/owl#sameAs"},"o":{"type":"uri","value":"http://nl.dbpedia.org/resource/Tokio"}},{"p":{"type":"uri","value":"http://www.w3.org/2002/07/owl#sameAs"},"o":{"type":"uri","value":"http://nn.dbpedia.org/resource/Tokyo"}},{"p":{"type":"uri","value":"http://www.w3.org/2002/07/owl#sameAs"},"o":{"type":"uri","value":"http://no.dbpedia.org/resource/Tokyo"}},{"p":{"type":"uri","value":"http://www.w3.org/2002/07/owl#sameAs"},"o":{"type":"uri","value":"http://oc.dbpedia.org/resource/Prefectura_de_Tòquio"}},{"p":{"type":"uri","value":"http://www.w3.org/2002/07/owl#sameAs"},"o":{"type":"uri","value":"http://pa.dbpedia.org/resource/ਟੋਕੀਓ"}},{"p":{"type":"uri","value":"http://www.w3.org/2002/07/owl#sameAs"},"o":{"type":"uri","value":"http://pl.dbpedia.org/resource/Tokio"}},{"p":{"type":"uri","value":"http://www.w3.org/2002/07/owl#sameAs"},"o":{"type":"uri","value":"http://pms.dbpedia.org/resource/Tokyo"}},{"p":{"type":"uri","value":"http://www.w3.org/2002/07/owl#sameAs"},"o":{"type":"uri","value":"http://pnb.dbpedia.org/resource/ٹوکیو"}},{"p":{"type":"uri","value":"http://www.w3.org/2002/07/owl#sameAs"},"o":{"type":"uri","value":"http://pt.dbpedia.org/resource/Tóquio"}},{"p":{"type":"uri","value":"http://www.w3.org/2002/07/owl#sameAs"},"o":{"type":"uri","value":"http://qu.dbpedia.org/resource/Tokyo"}},{"p":{"type":"uri","value":"http://www.w3.org/2002/07/owl#sameAs"},"o":{"type":"uri","value":"http://ro.dbpedia.org/resource/Tōkyō"}}]